basic_ops_calculator/__init__.py
basic_ops_calculator/operations/__init__.py
basic_ops_calculator/operations/advanced.py
basic_ops_calculator/operations/basic.py
basic_ops_calculator-0.0.1.dist-info/METADATA
basic_ops_calculator-0.0.1.dist-info/WHEEL
basic_ops_calculator-0.0.1.dist-info/top_level.txt
basic_ops_calculator-0.0.1.dist-info/RECORD
