Metadata-Version: 2.1
Name: basic-ops-calculator
Version: 0.0.1
Summary: A basic calculator, to test the package creation
Home-page: https://github.com/Marcelo-L-Valerio/DIO-DataScience-Bootcamp/tree/main/02-Criacao-de-pacotes
Author: Marcelo L Valerio
Author-email: mar.valerio@hotmail.com.br
Requires-Python: >=3.8
